src/launcher copy.py
src/launcher.py
image_vector_diego-0.1.0.dist-info/entry_points.txt
image_vector_diego-0.1.0.dist-info/METADATA
image_vector_diego-0.1.0.dist-info/WHEEL
image_vector_diego-0.1.0.dist-info/RECORD
