Metadata-Version: 2.1
Name: image_vector_diego
Version: 0.1.0
Summary: 
License: MIT
Author: heartfish00
Author-email: heartfish@naver.com
Requires-Python: >=3.11,<4.0
Classifier: License :: OSI Approved :: MIT License
Classifier: Programming Language :: Python :: 3
Classifier: Programming Language :: Python :: 3.11
Classifier: Programming Language :: Python :: 3.12
Requires-Dist: altair (==5.3.0)
Requires-Dist: altgraph (==0.17.4)
Requires-Dist: asttokens (==2.4.1)
Requires-Dist: attrs (==23.2.0)
Requires-Dist: blinker (==1.8.2)
Requires-Dist: brotli (==1.1.0)
Requires-Dist: cachetools (==5.4.0)
Requires-Dist: certifi (==2024.7.4)
Requires-Dist: charset-normalizer (==3.3.2)
Requires-Dist: click (==8.1.7)
Requires-Dist: colorama (==0.4.6)
Requires-Dist: comm (==0.2.2)
Requires-Dist: debugpy (==1.8.2)
Requires-Dist: decorator (==5.1.1)
Requires-Dist: exceptiongroup (==1.2.2)
Requires-Dist: executing (==2.0.1)
Requires-Dist: faiss-cpu (==1.8.0)
Requires-Dist: filelock (==3.15.3)
Requires-Dist: fsspec (==2024.6.0)
Requires-Dist: ftfy (==6.2.0)
Requires-Dist: gitdb (==4.0.11)
Requires-Dist: gitpython (==3.1.43)
Requires-Dist: idna (==3.7)
Requires-Dist: importlib-metadata (==8.2.0)
Requires-Dist: importlib-resources (==6.4.0)
Requires-Dist: ipykernel (==6.29.5)
Requires-Dist: ipython (==8.26.0)
Requires-Dist: ipywidgets (==8.1.3)
Requires-Dist: jedi (==0.19.1)
Requires-Dist: jinja2 (==3.1.4)
Requires-Dist: jsonschema (==4.23.0)
Requires-Dist: jsonschema-specifications (==2023.12.1)
Requires-Dist: jupyter-client (==8.6.2)
Requires-Dist: jupyter-core (==5.7.2)
Requires-Dist: jupyterlab-widgets (==3.0.11)
Requires-Dist: markdown-it-py (==3.0.0)
Requires-Dist: markupsafe (==2.1.5)
Requires-Dist: matplotlib-inline (==0.1.7)
Requires-Dist: mdurl (==0.1.2)
Requires-Dist: mpmath (==1.3.0)
Requires-Dist: nest-asyncio (==1.6.0)
Requires-Dist: networkx (==3.3)
Requires-Dist: numpy (==1.26.4)
Requires-Dist: openai-clip (==1.0.1)
Requires-Dist: packaging (==24.1)
Requires-Dist: pandas (==2.2.2)
Requires-Dist: parso (==0.8.4)
Requires-Dist: pefile (==2023.2.7)
Requires-Dist: pickleshare (==0.7.5)
Requires-Dist: pillow (==10.4.0)
Requires-Dist: pkgutil-resolve-name (==1.3.10)
Requires-Dist: platformdirs (==4.2.2)
Requires-Dist: prompt-toolkit (==3.0.47)
Requires-Dist: protobuf (==4.25.3)
Requires-Dist: psutil (==6.0.0)
Requires-Dist: pure-eval (==0.2.3)
Requires-Dist: pyarrow (==16.1.0)
Requires-Dist: pydeck (==0.9.1)
Requires-Dist: pygments (==2.18.0)
Requires-Dist: pyinstaller-hooks-contrib (==2024.7)
Requires-Dist: pyngrok (==7.1.6)
Requires-Dist: pysocks (==1.7.1)
Requires-Dist: python-dateutil (==2.9.0.post0)
Requires-Dist: pytz (==2024.1)
Requires-Dist: pywin32 (==306)
Requires-Dist: pywin32-ctypes (==0.2.2)
Requires-Dist: pyyaml (==6.0.1)
Requires-Dist: pyzmq (==26.0.3)
Requires-Dist: referencing (==0.35.1)
Requires-Dist: regex (==2024.5.15)
Requires-Dist: requests (==2.32.3)
Requires-Dist: rich (==13.7.1)
Requires-Dist: rpds-py (==0.19.1)
Requires-Dist: shiv (==1.0.6)
Requires-Dist: six (==1.16.0)
Requires-Dist: smmap (==5.0.1)
Requires-Dist: stack-data (==0.6.3)
Requires-Dist: streamlit (==1.37.0)
Requires-Dist: sympy (==1.12.1)
Requires-Dist: tenacity (==8.5.0)
Requires-Dist: toml (==0.10.2)
Requires-Dist: toolz (==0.12.1)
Requires-Dist: torch (==2.1.1)
Requires-Dist: torchaudio (==2.1.1)
Requires-Dist: torchvision (==0.16.1)
Requires-Dist: tornado (==6.4.1)
Requires-Dist: tqdm (==4.66.4)
Requires-Dist: traitlets (==5.14.3)
Requires-Dist: typing-extensions (==4.12.2)
Requires-Dist: tzdata (==2024.1)
Requires-Dist: tzlocal (==5.2)
Requires-Dist: urllib3 (==2.2.2)
Requires-Dist: validators (==0.33.0)
Requires-Dist: watchdog (==4.0.1)
Requires-Dist: wcwidth (==0.2.13)
Requires-Dist: widgetsnbextension (==4.0.11)
Requires-Dist: win-inet-pton (==1.1.0)
Requires-Dist: zipp (==3.19.2)
